[
	{
		"academy_id": 1,
		"language_id": 5,
		"name": "联邦学生会",
		"lorebook_id": 500031,
		"extra_key_words": "{\"long\": [\"你的学园\", \"你的学校\"]}"
	},
	{
		"academy_id": 2,
		"language_id": 5,
		"name": "阿拜多斯高中",
		"lorebook_id": 500032,
		"extra_key_words": "{\"long\": [\"你的学园\", \"你的学校\"]}"
	},
	{
		"academy_id": 3,
		"language_id": 5,
		"name": "格黑娜学园",
		"lorebook_id": 500033,
		"extra_key_words": "{\"long\": [\"你的学园\/社团\"], \"short\": [\"你的学园\", \"你的学校\"]}"
	},
	{
		"academy_id": 4,
		"language_id": 5,
		"name": "三一综合学园",
		"lorebook_id": 500034,
		"extra_key_words": "{\"long\": [\"你的学园\/社团\"], \"short\": [\"你的学园\", \"你的学校\"]}"
	},
	{
		"academy_id": 5,
		"language_id": 5,
		"name": "千年科学学园",
		"lorebook_id": 500035,
		"extra_key_words": "{\"long\": [\"你的学园\/社团\"], \"short\": [\"你的学园\", \"你的学校\"]}"
	},
	{
		"academy_id": 6,
		"language_id": 5,
		"name": "山海经高级中学",
		"lorebook_id": 500036,
		"extra_key_words": "{\"long\": [\"你的学园\/社团\"], \"short\": [\"你的学园\", \"你的学校\"]}"
	},
	{
		"academy_id": 7,
		"language_id": 5,
		"name": "红冬联邦学园",
		"lorebook_id": 500037,
		"extra_key_words": "{\"long\": [\"你的学园\/社团\"], \"short\": [\"你的学园\", \"你的学校\"]}"
	},
	{
		"academy_id": 8,
		"language_id": 5,
		"name": "SRT特殊学园",
		"lorebook_id": 500038,
		"extra_key_words": "{\"long\": [\"你的学园\/社团\"], \"short\": [\"你的学园\", \"你的学校\"]}"
	},
	{
		"academy_id": 9,
		"language_id": 5,
		"name": "阿里乌斯分校",
		"lorebook_id": 500039,
		"extra_key_words": "{\"long\": [\"你的学园\", \"你的学校\"]}"
	},
	{
		"academy_id": 10,
		"language_id": 5,
		"name": "瓦尔基里警察学园",
		"lorebook_id": 500040,
		"extra_key_words": "{\"long\": [\"你的学园\/社团\"], \"short\": [\"你的学园\", \"你的学校\"]}"
	},
	{
		"academy_id": 11,
		"language_id": 5,
		"name": "百鬼夜行联合学园",
		"lorebook_id": 500041,
		"extra_key_words": "{\"long\": [\"你的学园\/社团\", \"你的学园\/历史\", \"你的学园\/传说\"], \"short\": [\"你的学园\", \"你的学校\"]}"
	},
	{
		"academy_id": 12,
		"language_id": 5,
		"name": "海兰德铁道学园",
		"lorebook_id": 500130,
		"extra_key_words": "{\"long\": [\"你的学园\"]}"
	},
	{
		"academy_id": 13,
		"language_id": 5,
		"name": "盖玛特里亚",
		"lorebook_id": 500135,
		"extra_key_words": "{\"long\": [\"你的组织\"]}"
	}
]